keycardai/mcp/integrations/fastmcp/__init__.py
keycardai/mcp/integrations/fastmcp/provider.py
keycardai/mcp/integrations/fastmcp/testing/__init__.py
keycardai/mcp/integrations/fastmcp/testing/test_utils.py
keycardai_mcp_fastmcp-0.17.0.dist-info/METADATA
keycardai_mcp_fastmcp-0.17.0.dist-info/WHEEL
keycardai_mcp_fastmcp-0.17.0.dist-info/RECORD
