Metadata-Version: 2.4
Name: keycardai-mcp-fastmcp
Version: 0.17.0
Summary: FastMCP integration for Keycard OAuth client with automated token exchange and authentication
Project-URL: Homepage, https://github.com/keycardai/python-sdk
Project-URL: Repository, https://github.com/keycardai/python-sdk
Project-URL: Documentation, https://docs.keycardai.com
Project-URL: Issues, https://github.com/keycardai/python-sdk/issues
Author-email: Keycard <support@keycard.ai>
License: MIT
Keywords: authentication,fastmcp,keycard,mcp,model-context-protocol,oauth,token-exchange
Classifier: Development Status :: 3 - Alpha
Classifier: Intended Audience :: Developers
Classifier: License :: OSI Approved :: MIT License
Classifier: Operating System :: OS Independent
Classifier: Programming Language :: Python :: 3
Classifier: Programming Language :: Python :: 3.10
Classifier: Programming Language :: Python :: 3.11
Classifier: Programming Language :: Python :: 3.12
Classifier: Programming Language :: Python :: 3.13
Classifier: Topic :: Internet :: WWW/HTTP :: Session
Classifier: Topic :: Scientific/Engineering :: Artificial Intelligence
Classifier: Topic :: Security
Classifier: Topic :: Software Development :: Libraries :: Python Modules
Requires-Python: >=3.10
Requires-Dist: fastmcp==2.13.0
Requires-Dist: httpx>=0.27.2
Requires-Dist: keycardai-mcp>=0.15.0
Requires-Dist: keycardai-oauth>=0.6.0
Requires-Dist: pydantic-settings>=2.7.1
Requires-Dist: pydantic>=2.11.7
Provides-Extra: test
Requires-Dist: pytest-asyncio>=1.1.0; extra == 'test'
Requires-Dist: pytest>=8.4.1; extra == 'test'
